pulumi_sonarqube/__init__.py
pulumi_sonarqube/_inputs.py
pulumi_sonarqube/_utilities.py
pulumi_sonarqube/alm_azure.py
pulumi_sonarqube/alm_github.py
pulumi_sonarqube/alm_gitlab.py
pulumi_sonarqube/azure_binding.py
pulumi_sonarqube/get_group.py
pulumi_sonarqube/get_portfolio.py
pulumi_sonarqube/get_project.py
pulumi_sonarqube/get_qualitygate.py
pulumi_sonarqube/get_qualityprofile.py
pulumi_sonarqube/get_rule.py
pulumi_sonarqube/get_user.py
pulumi_sonarqube/github_binding.py
pulumi_sonarqube/gitlab_binding.py
pulumi_sonarqube/group.py
pulumi_sonarqube/group_member.py
pulumi_sonarqube/new_code_periods.py
pulumi_sonarqube/outputs.py
pulumi_sonarqube/permission_template.py
pulumi_sonarqube/permissions.py
pulumi_sonarqube/plugin.py
pulumi_sonarqube/portfolio.py
pulumi_sonarqube/project.py
pulumi_sonarqube/project_main_branch.py
pulumi_sonarqube/provider.py
pulumi_sonarqube/pulumi-plugin.json
pulumi_sonarqube/py.typed
pulumi_sonarqube/qualitygate.py
pulumi_sonarqube/qualitygate_project_association.py
pulumi_sonarqube/qualitygate_usergroup_association.py
pulumi_sonarqube/qualityprofile.py
pulumi_sonarqube/qualityprofile_activate_rule.py
pulumi_sonarqube/qualityprofile_project_association.py
pulumi_sonarqube/rule.py
pulumi_sonarqube/setting.py
pulumi_sonarqube/user.py
pulumi_sonarqube/user_external_identity.py
pulumi_sonarqube/user_token.py
pulumi_sonarqube/webhook.py
pulumi_sonarqube/config/__init__.py
pulumi_sonarqube/config/__init__.pyi
pulumi_sonarqube/config/vars.py
pulumi_sonarqube-1.0.0.dist-info/METADATA
pulumi_sonarqube-1.0.0.dist-info/WHEEL
pulumi_sonarqube-1.0.0.dist-info/top_level.txt
pulumi_sonarqube-1.0.0.dist-info/RECORD
